vlm_tools/api.py
vlm_tools/cli.py
vlm_tools/constants.py
vlm_tools/image.py
vlm_tools/utils.py
vlm_tools/video.py
vlm_tools-0.2.3.dist-info/LICENSE
vlm_tools-0.2.3.dist-info/METADATA
vlm_tools-0.2.3.dist-info/WHEEL
vlm_tools-0.2.3.dist-info/entry_points.txt
vlm_tools-0.2.3.dist-info/RECORD
