Metadata-Version: 2.1
Name: vlm-tools
Version: 0.2.3
Summary: Tools to work with the VLM-1 API.
Author: Sudeep Pillai
Author-email: sudeep.pillai@gmail.com
Requires-Python: >=3.10,<3.12
Classifier: Programming Language :: Python :: 3
Classifier: Programming Language :: Python :: 3.10
Classifier: Programming Language :: Python :: 3.11
Provides-Extra: dev
Provides-Extra: torch
Requires-Dist: loguru (>0.7.0)
Requires-Dist: numpy (>=1.26.0,<2.0.0)
Requires-Dist: pydantic[email] (>=2.7.1,<3.0.0)
Requires-Dist: python-dotenv (>=1.0.1,<2.0.0)
Requires-Dist: requests (>=2.31.0,<3.0.0)
Requires-Dist: torch (>=2.3.1,<3.0.0) ; extra == "torch"
Requires-Dist: torch-nos (>=0.3.0,<0.4.0)
Requires-Dist: torchvision (>=0.18.1,<0.19.0) ; extra == "torch"
Requires-Dist: transformers (>=4.41.2,<5.0.0) ; extra == "torch"
Requires-Dist: typer (>=0.12.3,<0.13.0)
